LICENSE
MANIFEST.in
README.md
pyproject.toml
setup.py
cconfetti.egg-info/PKG-INFO
cconfetti.egg-info/SOURCES.txt
cconfetti.egg-info/dependency_links.txt
cconfetti.egg-info/top_level.txt
confetti/confetti.c
confetti/confetti.h
confetti/confetti_unidata.c
confetti/unicode.py
confetti/tests/generate_tests.py
src/__init__.py
src/py_argument.c
src/py_confetti.c
src/py_confetti.h
src/py_directive.c
src/py_exception.c
src/py_parse.c
tests/__init__.py
tests/test_conformance.py