Metadata-Version: 2.4
Name: cconfetti
Version: 0.1.0
Summary: Confetti configuration language, official C bindings.
License-Expression: MIT
Project-URL: Source, https://github.com/hgs3/confetti-python.git
Classifier: Intended Audience :: Developers
Classifier: Programming Language :: Python
Classifier: Programming Language :: Python :: 3.12
Classifier: Programming Language :: Python :: 3.13
Classifier: Programming Language :: Python :: Implementation :: CPython
Classifier: Topic :: Documentation
Requires-Python: >=3.12
License-File: LICENSE
Dynamic: license-file
